odoo/addons/repair_picking/README.rst
odoo/addons/repair_picking/__init__.py
odoo/addons/repair_picking/__manifest__.py
odoo/addons/repair_picking/i18n/it.po
odoo/addons/repair_picking/i18n/repair_picking.pot
odoo/addons/repair_picking/migrations/17.0.1.0.0/pre-migration.py
odoo/addons/repair_picking/models/__init__.py
odoo/addons/repair_picking/models/procurement_group.py
odoo/addons/repair_picking/models/repair.py
odoo/addons/repair_picking/models/stock_move.py
odoo/addons/repair_picking/models/stock_warehouse.py
odoo/addons/repair_picking/readme/CONFIGURE.md
odoo/addons/repair_picking/readme/CONTRIBUTORS.md
odoo/addons/repair_picking/readme/DESCRIPTION.md
odoo/addons/repair_picking/readme/USAGE.md
odoo/addons/repair_picking/static/description/icon.png
odoo/addons/repair_picking/static/description/index.html
odoo/addons/repair_picking/tests/__init__.py
odoo/addons/repair_picking/tests/test_stock_repair_order.py
odoo/addons/repair_picking/tests/test_stock_repair_warehouse.py
odoo/addons/repair_picking/views/stock_warehouse_views.xml
odoo_addon_repair_picking-17.0.1.0.0.6.dist-info/METADATA
odoo_addon_repair_picking-17.0.1.0.0.6.dist-info/WHEEL
odoo_addon_repair_picking-17.0.1.0.0.6.dist-info/top_level.txt
odoo_addon_repair_picking-17.0.1.0.0.6.dist-info/RECORD
